envector-0.3.1.dist-info/METADATA
envector-0.3.1.dist-info/WHEEL
envector-0.3.1.dist-info/licenses/AUTHORS.rst
envector-0.3.1.dist-info/licenses/LICENSE.txt
envector/__init__.py
envector/_acknowledgements.py
envector/_common.py
envector/_documentation.py
envector/_examples.py
envector/_examples_object_oriented.py
envector/_images.py
envector/_info.py
envector/_info_functional.py
envector/_installation.py
envector/_intro.py
envector/core.py
envector/karney.py
envector/license.py
envector/objects.py
envector/plot.py
envector/rotation.py
envector/util.py
envector-0.3.1.dist-info/RECORD
