Metadata-Version: 2.1
Name: envector
Version: 0.3.1
Summary: The envector library is a suite of tools written in Python to solve geographical position calculations forked from nvector.
Author: Kenneth Gade, FFI, Kristian Svartveit, FFI, Brita Hafskjold Gade, FFI, Per A. Brodtkorb, FFI
Author-Email: Matt Hogan <mhogan@nwra.com>
License: Simplified BSD
Classifier: Programming Language :: Python :: 3
Classifier: Programming Language :: Python :: 3.9
Classifier: Programming Language :: Python :: 3.10
Classifier: Programming Language :: Python :: 3.11
Classifier: Programming Language :: Python :: 3.12
Classifier: Environment :: Console
Classifier: Intended Audience :: Education
Classifier: Intended Audience :: Science/Research
Classifier: License :: OSI Approved :: BSD License
Classifier: Operating System :: OS Independent
Classifier: Operating System :: POSIX :: Linux
Classifier: Operating System :: Unix
Classifier: Operating System :: MacOS
Classifier: Operating System :: Microsoft :: Windows
Classifier: Topic :: Scientific/Engineering :: Mathematics
Classifier: Topic :: Scientific/Engineering :: GIS
Project-URL: Repository, https://github.com/mhogan-nwra/envector/
Project-URL: Documentation, https://envector.readthedocs.io/en/latest/
Requires-Python: >=3.9
Requires-Dist: numpy>=1.11.0
Requires-Dist: scipy>=1.3.0
Requires-Dist: geographiclib>=2.0
Requires-Dist: matplotlib>=3.8.0
Requires-Dist: Cartopy>=0.22.0
